gtree/__init__.py
gtree/gtree.py
gtree-0.4.4.dist-info/LICENSE
gtree-0.4.4.dist-info/METADATA
gtree-0.4.4.dist-info/WHEEL
gtree-0.4.4.dist-info/top_level.txt
gtree-0.4.4.dist-info/RECORD
