Metadata-Version: 2.1
Name: gtree
Version: 0.4.4
Summary: A general tree implementation providing convinient methods for defining trees in JSON or YAML files.
Home-page: https://github.com/lunjon/gtree
Author: Jonathan Lundholm
Author-email: jon.lundholm@gmail.com
License: MIT
Platform: UNKNOWN
Classifier: Programming Language :: Python :: 3
Classifier: License :: OSI Approved :: MIT License
Classifier: Operating System :: OS Independent
